{
  "mode": "osm",
  "scenario": "1pct",
  "bbox": [
    52.4828,
    13.2136,
    52.5330,
    13.3594
  ],
  "simulationDate": "02.02.2020",
  "pollutant": "PM10",
  "zoneUpdateInterval": 60,
  "averagingMethod": "weighted",
  "averagingInterval": 60,
  "interpolationMethod": "idw",
  "zones": [
    0,
    20,
    35,
    50,
    100,
    1000
  ],
  "periodicRerouting": true,
  "zoneRerouting": "none",
  "reroutingDecisionMode": "percent",
  "reroutingPercent": 1,
  "dynamicReroutingDistance": 300,
  "snapshotZones": false,
  "rerouteOnZoneUpdate": false,
  "nonDepartDecisionMode": "percent",
  "nonDepartPercent": 0,
  "mesosim": false,
  "libsumo": false
}